{"moduleDefinition":{"range":[1,1,1,37],"value":{"type":"normal","normal":{"moduleName":{"range":[1,8,1,23],"value":["ProductsManager"]},"exposingList":{"range":[1,24,1,37],"value":{"type":"all","all":[1,34,1,36]}}}}},"imports":[{"range":[3,1,3,15],"value":{"moduleName":{"range":[3,8,3,15],"value":["Browser"]},"moduleAlias":null,"exposingList":null}},{"range":[4,1,4,31],"value":{"moduleName":{"range":[4,8,4,17],"value":["Bulma","CDN"]},"moduleAlias":null,"exposingList":{"range":[4,18,4,31],"value":{"type":"all","all":[4,28,4,30]}}}},{"range":[5,1,5,35],"value":{"moduleName":{"range":[5,8,5,21],"value":["Bulma","Columns"]},"moduleAlias":null,"exposingList":{"range":[5,22,5,35],"value":{"type":"all","all":[5,32,5,34]}}}},{"range":[6,1,6,38],"value":{"moduleName":{"range":[6,8,6,24],"value":["Bulma","Components"]},"moduleAlias":null,"exposingList":{"range":[6,25,6,38],"value":{"type":"all","all":[6,35,6,37]}}}},{"range":[7,1,7,36],"value":{"moduleName":{"range":[7,8,7,22],"value":["Bulma","Elements"]},"moduleAlias":null,"exposingList":{"range":[7,23,7,36],"value":{"type":"all","all":[7,33,7,35]}}}},{"range":[8,1,8,32],"value":{"moduleName":{"range":[8,8,8,18],"value":["Bulma","Form"]},"moduleAlias":null,"exposingList":{"range":[8,19,8,32],"value":{"type":"all","all":[8,29,8,31]}}}},{"range":[9,1,9,34],"value":{"moduleName":{"range":[9,8,9,20],"value":["Bulma","Layout"]},"moduleAlias":null,"exposingList":{"range":[9,21,9,34],"value":{"type":"all","all":[9,31,9,33]}}}},{"range":[10,1,17,10],"value":{"moduleName":{"range":[10,8,10,23],"value":["Bulma","Modifiers"]},"moduleAlias":null,"exposingList":{"range":[11,5,17,10],"value":{"type":"explicit","explicit":[{"range":[12,11,12,20],"value":{"type":"typeexpose","typeexpose":{"name":"Color","open":[12,16,12,20]}}},{"range":[13,11,13,34],"value":{"type":"typeexpose","typeexpose":{"name":"HorizontalAlignment","open":[13,30,13,34]}}},{"range":[14,11,14,19],"value":{"type":"typeexpose","typeexpose":{"name":"Size","open":[14,15,14,19]}}},{"range":[15,11,15,20],"value":{"type":"typeexpose","typeexpose":{"name":"State","open":[15,16,15,20]}}},{"range":[16,11,16,32],"value":{"type":"typeexpose","typeexpose":{"name":"VerticalDirection","open":[16,28,16,32]}}}]}}}},{"range":[18,1,18,26],"value":{"moduleName":{"range":[18,8,18,12],"value":["Html"]},"moduleAlias":null,"exposingList":{"range":[18,13,18,26],"value":{"type":"all","all":[18,23,18,25]}}}},{"range":[19,1,19,38],"value":{"moduleName":{"range":[19,8,19,19],"value":["Html","Events"]},"moduleAlias":null,"exposingList":{"range":[19,20,19,38],"value":{"type":"explicit","explicit":[{"range":[19,30,19,37],"value":{"type":"function","function":{"name":"onClick"}}}]}}}},{"range":[20,1,20,26],"value":{"moduleName":{"range":[20,8,20,12],"value":["Http"]},"moduleAlias":null,"exposingList":{"range":[20,13,20,26],"value":{"type":"all","all":[20,23,20,25]}}}},{"range":[21,1,21,43],"value":{"moduleName":{"range":[21,8,21,19],"value":["Json","Decode"]},"moduleAlias":{"range":[21,23,21,29],"value":["Decode"]},"exposingList":{"range":[21,30,21,43],"value":{"type":"all","all":[21,40,21,42]}}}},{"range":[22,1,22,42],"value":{"moduleName":{"range":[22,8,22,28],"value":["Json","Decode","Pipeline"]},"moduleAlias":null,"exposingList":{"range":[22,29,22,42],"value":{"type":"all","all":[22,39,22,41]}}}}],"declarations":[{"range":[29,1,35,10],"value":{"type":"function","function":{"documentation":null,"signature":null,"declaration":{"range":[29,1,35,10],"value":{"name":{"range":[29,1,29,5],"value":"main"},"arguments":[],"expression":{"range":[30,5,35,10],"value":{"type":"application","application":[{"range":[30,5,30,20],"value":{"type":"functionOrValue","functionOrValue":{"moduleName":["Browser"],"name":"element"}}},{"range":[31,9,35,10],"value":{"type":"record","record":[{"range":[31,11,31,78],"value":{"field":{"range":[31,11,31,15],"value":"init"},"expression":{"range":[31,18,31,78],"value":{"type":"application","application":[{"range":[31,18,31,24],"value":{"type":"functionOrValue","functionOrValue":{"moduleName":[],"name":"always"}}},{"range":[31,25,31,78],"value":{"type":"tupled","tupled":[{"range":[31,27,31,66],"value":{"type":"record","record":[{"range":[31,29,31,47],"value":{"field":{"range":[31,29,31,37],"value":"products"},"expression":{"range":[31,40,31,47],"value":{"type":"functionOrValue","functionOrValue":{"moduleName":[],"name":"Nothing"}}}}},{"range":[31,49,31,65],"value":{"field":{"range":[31,49,31,53],"value":"page"},"expression":{"range":[31,56,31,64],"value":{"type":"functionOrValue","functionOrValue":{"moduleName":[],"name":"Products"}}}}}]}},{"range":[31,68,31,76],"value":{"type":"functionOrValue","functionOrValue":{"moduleName":["Cmd"],"name":"none"}}}]}}]}}}},{"range":[32,11,33,9],"value":{"field":{"range":[32,11,32,24],"value":"subscriptions"},"expression":{"range":[32,27,32,31],"value":{"type":"functionOrValue","functionOrValue":{"moduleName":[],"name":"subs"}}}}},{"range":[33,11,34,9],"value":{"field":{"range":[33,11,33,17],"value":"update"},"expression":{"range":[33,20,33,26],"value":{"type":"functionOrValue","functionOrValue":{"moduleName":[],"name":"update"}}}}},{"range":[34,11,35,9],"value":{"field":{"range":[34,11,34,15],"value":"view"},"expression":{"range":[34,18,34,22],"value":{"type":"functionOrValue","functionOrValue":{"moduleName":[],"name":"view"}}}}}]}}]}}}}}}},{"range":[38,1,40,13],"value":{"type":"function","function":{"documentation":null,"signature":{"range":[38,1,38,24],"value":{"name":{"range":[38,1,38,5],"value":"subs"},"typeAnnotation":{"range":[38,8,38,24],"value":{"type":"function","function":{"left":{"range":[38,8,38,13],"value":{"type":"generic","generic":{"value":"model"}}},"right":{"range":[38,17,38,24],"value":{"type":"typed","typed":{"moduleNameAndName":{"range":[38,17,38,20],"value":{"moduleName":[],"name":"Sub"}},"args":[{"range":[38,21,38,24],"value":{"type":"generic","generic":{"value":"msg"}}}]}}}}}}}},"declaration":{"range":[39,1,40,13],"value":{"name":{"range":[39,1,39,5],"value":"subs"},"arguments":[{"range":[39,6,39,11],"value":{"type":"var","var":{"value":"model"}}}],"expression":{"range":[40,5,40,13],"value":{"type":"functionOrValue","functionOrValue":{"moduleName":["Sub"],"name":"none"}}}}}}}},{"range":[47,1,50,18],"value":{"type":"typedecl","typedecl":{"documentation":null,"name":{"range":[47,6,47,18],"value":"Availability"},"generics":[],"constructors":[{"range":[48,7,48,13],"value":{"name":{"range":[48,7,48,13],"value":"InCart"},"arguments":[]}},{"range":[49,7,49,15],"value":{"name":{"range":[49,7,49,15],"value":"Avalible"},"arguments":[]}},{"range":[50,7,50,18],"value":{"name":{"range":[50,7,50,18],"value":"UnAvailable"},"arguments":[]}}]}}},{"range":[53,1,59,6],"value":{"type":"typeAlias","typeAlias":{"documentation":null,"name":{"range":[53,12,53,19],"value":"Product"},"generics":[],"typeAnnotation":{"range":[54,5,59,6],"value":{"type":"record","record":{"value":[{"range":[54,7,54,15],"value":{"name":{"range":[54,7,54,9],"value":"id"},"typeAnnotation":{"range":[54,12,54,15],"value":{"type":"typed","typed":{"moduleNameAndName":{"range":[54,12,54,15],"value":{"moduleName":[],"name":"Int"}},"args":[]}}}}},{"range":[55,5,56,5],"value":{"name":{"range":[55,7,55,11],"value":"name"},"typeAnnotation":{"range":[55,14,55,20],"value":{"type":"typed","typed":{"moduleNameAndName":{"range":[55,14,55,20],"value":{"moduleName":[],"name":"String"}},"args":[]}}}}},{"range":[56,5,57,5],"value":{"name":{"range":[56,7,56,12],"value":"price"},"typeAnnotation":{"range":[56,15,56,18],"value":{"type":"typed","typed":{"moduleNameAndName":{"range":[56,15,56,18],"value":{"moduleName":[],"name":"Int"}},"args":[]}}}}},{"range":[57,5,58,5],"value":{"name":{"range":[57,7,57,14],"value":"inStock"},"typeAnnotation":{"range":[57,17,57,20],"value":{"type":"typed","typed":{"moduleNameAndName":{"range":[57,17,57,20],"value":{"moduleName":[],"name":"Int"}},"args":[]}}}}},{"range":[58,5,59,5],"value":{"name":{"range":[58,7,58,12],"value":"avail"},"typeAnnotation":{"range":[58,15,58,27],"value":{"type":"typed","typed":{"moduleNameAndName":{"range":[58,15,58,27],"value":{"moduleName":[],"name":"Availability"}},"args":[]}}}}}]}}}}}},{"range":[66,1,67,26],"value":{"type":"function","function":{"documentation":null,"signature":null,"declaration":{"range":[66,1,67,26],"value":{"name":{"range":[66,1,66,7],"value":"apiurl"},"arguments":[],"expression":{"range":[67,5,67,26],"value":{"type":"literal","literal":"localhost:51786/api"}}}}}}},{"range":[70,1,73,6],"value":{"type":"typeAlias","typeAlias":{"documentation":null,"name":{"range":[70,12,70,17],"value":"Model"},"generics":[],"typeAnnotation":{"range":[71,5,73,6],"value":{"type":"record","record":{"value":[{"range":[71,7,71,38],"value":{"name":{"range":[71,7,71,15],"value":"products"},"typeAnnotation":{"range":[71,18,71,38],"value":{"type":"typed","typed":{"moduleNameAndName":{"range":[71,18,71,23],"value":{"moduleName":[],"name":"Maybe"}},"args":[{"range":[71,24,71,38],"value":{"type":"typed","typed":{"moduleNameAndName":{"range":[71,25,71,29],"value":{"moduleName":[],"name":"List"}},"args":[{"range":[71,30,71,37],"value":{"type":"typed","typed":{"moduleNameAndName":{"range":[71,30,71,37],"value":{"moduleName":[],"name":"Product"}},"args":[]}}}]}}}]}}}}},{"range":[72,5,73,5],"value":{"name":{"range":[72,7,72,11],"value":"page"},"typeAnnotation":{"range":[72,14,72,18],"value":{"type":"typed","typed":{"moduleNameAndName":{"range":[72,14,72,18],"value":{"moduleName":[],"name":"Page"}},"args":[]}}}}}]}}}}}},{"range":[76,1,79,22],"value":{"type":"typedecl","typedecl":{"documentation":null,"name":{"range":[76,6,76,9],"value":"Msg"},"generics":[],"constructors":[{"range":[77,7,77,19],"value":{"name":{"range":[77,7,77,19],"value":"LoadProducts"},"arguments":[]}},{"range":[78,7,78,56],"value":{"name":{"range":[78,7,78,21],"value":"ProductsLoaded"},"arguments":[{"range":[78,22,78,56],"value":{"type":"typed","typed":{"moduleNameAndName":{"range":[78,23,78,29],"value":{"moduleName":[],"name":"Result"}},"args":[{"range":[78,30,78,40],"value":{"type":"typed","typed":{"moduleNameAndName":{"range":[78,30,78,40],"value":{"moduleName":["Http"],"name":"Error"}},"args":[]}}},{"range":[78,41,78,55],"value":{"type":"typed","typed":{"moduleNameAndName":{"range":[78,42,78,46],"value":{"moduleName":[],"name":"List"}},"args":[{"range":[78,47,78,54],"value":{"type":"typed","typed":{"moduleNameAndName":{"range":[78,47,78,54],"value":{"moduleName":[],"name":"Product"}},"args":[]}}}]}}}]}}}]}},{"range":[79,7,79,22],"value":{"name":{"range":[79,7,79,17],"value":"ChangePage"},"arguments":[{"range":[79,18,79,22],"value":{"type":"typed","typed":{"moduleNameAndName":{"range":[79,18,79,22],"value":{"moduleName":[],"name":"Page"}},"args":[]}}}]}}]}}},{"range":[82,1,87,18],"value":{"type":"typedecl","typedecl":{"documentation":null,"name":{"range":[82,6,82,10],"value":"Page"},"generics":[],"constructors":[{"range":[83,7,83,15],"value":{"name":{"range":[83,7,83,15],"value":"Products"},"arguments":[]}},{"range":[84,7,84,20],"value":{"name":{"range":[84,7,84,20],"value":"ProductDetail"},"arguments":[]}},{"range":[85,7,85,11],"value":{"name":{"range":[85,7,85,11],"value":"Cart"},"arguments":[]}},{"range":[86,7,86,19],"value":{"name":{"range":[86,7,86,19],"value":"OrderHistory"},"arguments":[]}},{"range":[87,7,87,18],"value":{"name":{"range":[87,7,87,18],"value":"OrderDetail"},"arguments":[]}}]}}},{"range":[94,1,115,14],"value":{"type":"function","function":{"documentation":null,"signature":{"range":[94,1,94,44],"value":{"name":{"range":[94,1,94,7],"value":"update"},"typeAnnotation":{"range":[94,10,94,44],"value":{"type":"function","function":{"left":{"range":[94,10,94,13],"value":{"type":"typed","typed":{"moduleNameAndName":{"range":[94,10,94,13],"value":{"moduleName":[],"name":"Msg"}},"args":[]}}},"right":{"range":[94,17,94,44],"value":{"type":"function","function":{"left":{"range":[94,17,94,22],"value":{"type":"typed","typed":{"moduleNameAndName":{"range":[94,17,94,22],"value":{"moduleName":[],"name":"Model"}},"args":[]}}},"right":{"range":[94,26,94,44],"value":{"type":"tupled","tupled":{"values":[{"range":[94,28,94,33],"value":{"type":"typed","typed":{"moduleNameAndName":{"range":[94,28,94,33],"value":{"moduleName":[],"name":"Model"}},"args":[]}}},{"range":[94,35,94,42],"value":{"type":"typed","typed":{"moduleNameAndName":{"range":[94,35,94,38],"value":{"moduleName":[],"name":"Cmd"}},"args":[{"range":[94,39,94,42],"value":{"type":"typed","typed":{"moduleNameAndName":{"range":[94,39,94,42],"value":{"moduleName":[],"name":"Msg"}},"args":[]}}}]}}}]}}}}}}}}}}},"declaration":{"range":[95,1,115,14],"value":{"name":{"range":[95,1,95,7],"value":"update"},"arguments":[{"range":[95,8,95,11],"value":{"type":"var","var":{"value":"msg"}}},{"range":[95,12,95,17],"value":{"type":"var","var":{"value":"model"}}}],"expression":{"range":[97,5,115,14],"value":{"type":"case","case":{"cases":[{"pattern":{"range":[98,9,98,21],"value":{"type":"named","named":{"qualified":{"moduleName":[],"name":"LoadProducts"},"patterns":[]}}},"expression":{"range":[99,13,99,36],"value":{"type":"application","application":[{"range":[99,13,99,30],"value":{"type":"functionOrValue","functionOrValue":{"moduleName":[],"name":"handleLoadProduct"}}},{"range":[99,31,99,36],"value":{"type":"functionOrValue","functionOrValue":{"moduleName":[],"name":"model"}}}]}}},{"pattern":{"range":[101,9,101,25],"value":{"type":"named","named":{"qualified":{"moduleName":[],"name":"ChangePage"},"patterns":[{"range":[101,20,101,25],"value":{"type":"var","var":{"value":"page_"}}}]}}},"expression":{"range":[102,13,102,51],"value":{"type":"tupled","tupled":[{"range":[102,15,102,39],"value":{"type":"recordUpdate","recordUpdate":{"name":{"range":[102,17,102,22],"value":"model"},"updates":[{"range":[102,25,102,38],"value":{"field":{"range":[102,25,102,29],"value":"page"},"expression":{"range":[102,32,102,37],"value":{"type":"functionOrValue","functionOrValue":{"moduleName":[],"name":"page_"}}}}}]}}},{"range":[102,41,102,49],"value":{"type":"functionOrValue","functionOrValue":{"moduleName":["Cmd"],"name":"none"}}}]}}},{"pattern":{"range":[104,9,104,33],"value":{"type":"named","named":{"qualified":{"moduleName":[],"name":"ProductsLoaded"},"patterns":[{"range":[104,24,104,33],"value":{"type":"var","var":{"value":"lproducts"}}}]}}},"expression":{"range":[105,13,115,14],"value":{"type":"tupled","tupled":[{"range":[105,15,113,16],"value":{"type":"recordUpdate","recordUpdate":{"name":{"range":[105,17,105,22],"value":"model"},"updates":[{"range":[106,19,113,15],"value":{"field":{"range":[106,19,106,27],"value":"products"},"expression":{"range":[107,21,112,36],"value":{"type":"case","case":{"cases":[{"pattern":{"range":[108,25,108,36],"value":{"type":"named","named":{"qualified":{"moduleName":[],"name":"Ok"},"patterns":[{"range":[108,28,108,36],"value":{"type":"var","var":{"value":"products"}}}]}}},"expression":{"range":[109,29,109,42],"value":{"type":"application","application":[{"range":[109,29,109,33],"value":{"type":"functionOrValue","functionOrValue":{"moduleName":[],"name":"Just"}}},{"range":[109,34,109,42],"value":{"type":"functionOrValue","functionOrValue":{"moduleName":[],"name":"products"}}}]}}},{"pattern":{"range":[111,25,111,34],"value":{"type":"named","named":{"qualified":{"moduleName":[],"name":"Err"},"patterns":[{"range":[111,29,111,34],"value":{"type":"var","var":{"value":"error"}}}]}}},"expression":{"range":[112,29,112,36],"value":{"type":"functionOrValue","functionOrValue":{"moduleName":[],"name":"Nothing"}}}}],"expression":{"range":[107,26,107,35],"value":{"type":"functionOrValue","functionOrValue":{"moduleName":[],"name":"lproducts"}}}}}}}}]}}},{"range":[114,15,114,23],"value":{"type":"functionOrValue","functionOrValue":{"moduleName":["Cmd"],"name":"none"}}}]}}}],"expression":{"range":[97,10,97,13],"value":{"type":"functionOrValue","functionOrValue":{"moduleName":[],"name":"msg"}}}}}}}}}}},{"range":[122,1,124,28],"value":{"type":"function","function":{"documentation":null,"signature":{"range":[122,1,122,48],"value":{"name":{"range":[122,1,122,18],"value":"handleLoadProduct"},"typeAnnotation":{"range":[122,21,122,48],"value":{"type":"function","function":{"left":{"range":[122,21,122,26],"value":{"type":"typed","typed":{"moduleNameAndName":{"range":[122,21,122,26],"value":{"moduleName":[],"name":"Model"}},"args":[]}}},"right":{"range":[122,30,122,48],"value":{"type":"tupled","tupled":{"values":[{"range":[122,32,122,37],"value":{"type":"typed","typed":{"moduleNameAndName":{"range":[122,32,122,37],"value":{"moduleName":[],"name":"Model"}},"args":[]}}},{"range":[122,39,122,46],"value":{"type":"typed","typed":{"moduleNameAndName":{"range":[122,39,122,42],"value":{"moduleName":[],"name":"Cmd"}},"args":[{"range":[122,43,122,46],"value":{"type":"typed","typed":{"moduleNameAndName":{"range":[122,43,122,46],"value":{"moduleName":[],"name":"Msg"}},"args":[]}}}]}}}]}}}}}}}},"declaration":{"range":[123,1,124,28],"value":{"name":{"range":[123,1,123,18],"value":"handleLoadProduct"},"arguments":[{"range":[123,19,123,24],"value":{"type":"var","var":{"value":"model"}}}],"expression":{"range":[124,5,124,28],"value":{"type":"tupled","tupled":[{"range":[124,7,124,12],"value":{"type":"functionOrValue","functionOrValue":{"moduleName":[],"name":"model"}}},{"range":[124,14,124,26],"value":{"type":"functionOrValue","functionOrValue":{"moduleName":[],"name":"loadProducts"}}}]}}}}}}},{"range":[127,1,132,10],"value":{"type":"function","function":{"documentation":null,"signature":{"range":[127,1,127,23],"value":{"name":{"range":[127,1,127,13],"value":"loadProducts"},"typeAnnotation":{"range":[127,16,127,23],"value":{"type":"typed","typed":{"moduleNameAndName":{"range":[127,16,127,19],"value":{"moduleName":[],"name":"Cmd"}},"args":[{"range":[127,20,127,23],"value":{"type":"typed","typed":{"moduleNameAndName":{"range":[127,20,127,23],"value":{"moduleName":[],"name":"Msg"}},"args":[]}}}]}}}}},"declaration":{"range":[128,1,132,10],"value":{"name":{"range":[128,1,128,13],"value":"loadProducts"},"arguments":[],"expression":{"range":[129,5,132,10],"value":{"type":"application","application":[{"range":[129,5,129,13],"value":{"type":"functionOrValue","functionOrValue":{"moduleName":["Http"],"name":"get"}}},{"range":[130,9,132,10],"value":{"type":"record","record":[{"range":[130,11,130,38],"value":{"field":{"range":[130,11,130,14],"value":"url"},"expression":{"range":[130,17,130,38],"value":{"type":"application","application":[{"range":[130,17,130,23],"value":{"type":"functionOrValue","functionOrValue":{"moduleName":[],"name":"apiurl"}}},{"range":[130,24,130,26],"value":{"type":"operator","operator":"++"}},{"range":[130,27,130,38],"value":{"type":"literal","literal":"/Products"}}]}}}},{"range":[131,11,132,9],"value":{"field":{"range":[131,11,131,17],"value":"expect"},"expression":{"range":[131,20,131,80],"value":{"type":"application","application":[{"range":[131,20,131,35],"value":{"type":"functionOrValue","functionOrValue":{"moduleName":["Http"],"name":"expectJson"}}},{"range":[131,36,131,50],"value":{"type":"functionOrValue","functionOrValue":{"moduleName":[],"name":"ProductsLoaded"}}},{"range":[131,51,131,80],"value":{"type":"functionOrValue","functionOrValue":{"moduleName":[],"name":"getAllProductsResponseDecoder"}}}]}}}}]}}]}}}}}}},{"range":[135,1,137,31],"value":{"type":"function","function":{"documentation":null,"signature":{"range":[135,1,135,62],"value":{"name":{"range":[135,1,135,30],"value":"getAllProductsResponseDecoder"},"typeAnnotation":{"range":[135,33,135,62],"value":{"type":"typed","typed":{"moduleNameAndName":{"range":[135,33,135,47],"value":{"moduleName":["Decode"],"name":"Decoder"}},"args":[{"range":[135,48,135,62],"value":{"type":"typed","typed":{"moduleNameAndName":{"range":[135,49,135,53],"value":{"moduleName":[],"name":"List"}},"args":[{"range":[135,54,135,61],"value":{"type":"typed","typed":{"moduleNameAndName":{"range":[135,54,135,61],"value":{"moduleName":[],"name":"Product"}},"args":[]}}}]}}}]}}}}},"declaration":{"range":[136,1,137,31],"value":{"name":{"range":[136,1,136,30],"value":"getAllProductsResponseDecoder"},"arguments":[],"expression":{"range":[137,5,137,31],"value":{"type":"application","application":[{"range":[137,5,137,16],"value":{"type":"functionOrValue","functionOrValue":{"moduleName":["Decode"],"name":"list"}}},{"range":[137,17,137,31],"value":{"type":"functionOrValue","functionOrValue":{"moduleName":[],"name":"productDecoder"}}}]}}}}}}},{"range":[140,1,147,75],"value":{"type":"function","function":{"documentation":null,"signature":{"range":[140,1,140,40],"value":{"name":{"range":[140,1,140,15],"value":"productDecoder"},"typeAnnotation":{"range":[140,18,140,40],"value":{"type":"typed","typed":{"moduleNameAndName":{"range":[140,18,140,32],"value":{"moduleName":["Decode"],"name":"Decoder"}},"args":[{"range":[140,33,140,40],"value":{"type":"typed","typed":{"moduleNameAndName":{"range":[140,33,140,40],"value":{"moduleName":[],"name":"Product"}},"args":[]}}}]}}}}},"declaration":{"range":[141,1,147,75],"value":{"name":{"range":[141,1,141,15],"value":"productDecoder"},"arguments":[],"expression":{"range":[142,5,147,75],"value":{"type":"application","application":[{"range":[142,5,142,19],"value":{"type":"functionOrValue","functionOrValue":{"moduleName":["Decode"],"name":"succeed"}}},{"range":[142,20,142,27],"value":{"type":"functionOrValue","functionOrValue":{"moduleName":[],"name":"Product"}}},{"range":[143,9,143,11],"value":{"type":"operator","operator":"|>"}},{"range":[143,12,143,20],"value":{"type":"functionOrValue","functionOrValue":{"moduleName":[],"name":"required"}}},{"range":[143,21,143,25],"value":{"type":"literal","literal":"id"}},{"range":[143,26,143,36],"value":{"type":"functionOrValue","functionOrValue":{"moduleName":["Decode"],"name":"int"}}},{"range":[144,9,144,11],"value":{"type":"operator","operator":"|>"}},{"range":[144,12,144,20],"value":{"type":"functionOrValue","functionOrValue":{"moduleName":[],"name":"required"}}},{"range":[144,21,144,27],"value":{"type":"literal","literal":"name"}},{"range":[144,28,144,41],"value":{"type":"functionOrValue","functionOrValue":{"moduleName":["Decode"],"name":"string"}}},{"range":[145,9,145,11],"value":{"type":"operator","operator":"|>"}},{"range":[145,12,145,20],"value":{"type":"functionOrValue","functionOrValue":{"moduleName":[],"name":"required"}}},{"range":[145,21,145,28],"value":{"type":"literal","literal":"price"}},{"range":[145,29,145,39],"value":{"type":"functionOrValue","functionOrValue":{"moduleName":["Decode"],"name":"int"}}},{"range":[146,9,146,11],"value":{"type":"operator","operator":"|>"}},{"range":[146,12,146,20],"value":{"type":"functionOrValue","functionOrValue":{"moduleName":[],"name":"required"}}},{"range":[146,21,146,30],"value":{"type":"literal","literal":"inStock"}},{"range":[146,31,146,41],"value":{"type":"functionOrValue","functionOrValue":{"moduleName":["Decode"],"name":"int"}}},{"range":[147,9,147,11],"value":{"type":"operator","operator":"|>"}},{"range":[147,12,147,20],"value":{"type":"functionOrValue","functionOrValue":{"moduleName":[],"name":"required"}}},{"range":[147,21,147,42],"value":{"type":"literal","literal":"productAvailability"}},{"range":[147,43,147,75],"value":{"type":"parenthesized","parenthesized":{"range":[147,44,147,74],"value":{"type":"application","application":[{"range":[147,44,147,63],"value":{"type":"functionOrValue","functionOrValue":{"moduleName":[],"name":"availabilityDecoder"}}},{"range":[147,64,147,74],"value":{"type":"functionOrValue","functionOrValue":{"moduleName":["Decode"],"name":"int"}}}]}}}}]}}}}}}},{"range":[150,1,168,10],"value":{"type":"function","function":{"documentation":null,"signature":{"range":[150,1,150,72],"value":{"name":{"range":[150,1,150,20],"value":"availabilityDecoder"},"typeAnnotation":{"range":[150,23,150,72],"value":{"type":"function","function":{"left":{"range":[150,23,150,41],"value":{"type":"typed","typed":{"moduleNameAndName":{"range":[150,23,150,37],"value":{"moduleName":["Decode"],"name":"Decoder"}},"args":[{"range":[150,38,150,41],"value":{"type":"typed","typed":{"moduleNameAndName":{"range":[150,38,150,41],"value":{"moduleName":[],"name":"Int"}},"args":[]}}}]}}},"right":{"range":[150,45,150,72],"value":{"type":"typed","typed":{"moduleNameAndName":{"range":[150,45,150,59],"value":{"moduleName":["Decode"],"name":"Decoder"}},"args":[{"range":[150,60,150,72],"value":{"type":"typed","typed":{"moduleNameAndName":{"range":[150,60,150,72],"value":{"moduleName":[],"name":"Availability"}},"args":[]}}}]}}}}}}}},"declaration":{"range":[151,1,168,10],"value":{"name":{"range":[151,1,151,20],"value":"availabilityDecoder"},"arguments":[],"expression":{"range":[152,5,168,10],"value":{"type":"application","application":[{"range":[152,5,152,19],"value":{"type":"functionOrValue","functionOrValue":{"moduleName":["Decode"],"name":"andThen"}}},{"range":[153,9,168,10],"value":{"type":"parenthesized","parenthesized":{"range":[153,10,168,9],"value":{"type":"lambda","lambda":{"patterns":[{"range":[153,11,153,12],"value":{"type":"var","var":{"value":"x"}}}],"expression":{"range":[154,13,167,34],"value":{"type":"application","application":[{"range":[154,13,166,14],"value":{"type":"parenthesized","parenthesized":{"range":[154,14,165,32],"value":{"type":"case","case":{"cases":[{"pattern":{"range":[155,17,155,18],"value":{"type":"int","int":{"value":0}}},"expression":{"range":[156,21,156,27],"value":{"type":"functionOrValue","functionOrValue":{"moduleName":[],"name":"InCart"}}}},{"pattern":{"range":[158,17,158,18],"value":{"type":"int","int":{"value":1}}},"expression":{"range":[159,21,159,29],"value":{"type":"functionOrValue","functionOrValue":{"moduleName":[],"name":"Avalible"}}}},{"pattern":{"range":[161,17,161,18],"value":{"type":"int","int":{"value":2}}},"expression":{"range":[162,21,162,32],"value":{"type":"functionOrValue","functionOrValue":{"moduleName":[],"name":"UnAvailable"}}}},{"pattern":{"range":[164,17,164,18],"value":{"type":"all","all":{}}},"expression":{"range":[165,21,165,32],"value":{"type":"functionOrValue","functionOrValue":{"moduleName":[],"name":"UnAvailable"}}}}],"expression":{"range":[154,19,154,20],"value":{"type":"functionOrValue","functionOrValue":{"moduleName":[],"name":"x"}}}}}}}},{"range":[167,17,167,19],"value":{"type":"operator","operator":"|>"}},{"range":[167,20,167,34],"value":{"type":"functionOrValue","functionOrValue":{"moduleName":["Decode"],"name":"succeed"}}}]}}}}}}}]}}}}}}},{"range":[171,1,174,11],"value":{"type":"function","function":{"documentation":null,"signature":{"range":[171,1,171,25],"value":{"name":{"range":[171,1,171,5],"value":"view"},"typeAnnotation":{"range":[171,8,171,25],"value":{"type":"function","function":{"left":{"range":[171,8,171,13],"value":{"type":"typed","typed":{"moduleNameAndName":{"range":[171,8,171,13],"value":{"moduleName":[],"name":"Model"}},"args":[]}}},"right":{"range":[171,17,171,25],"value":{"type":"typed","typed":{"moduleNameAndName":{"range":[171,17,171,21],"value":{"moduleName":[],"name":"Html"}},"args":[{"range":[171,22,171,25],"value":{"type":"typed","typed":{"moduleNameAndName":{"range":[171,22,171,25],"value":{"moduleName":[],"name":"Msg"}},"args":[]}}}]}}}}}}}},"declaration":{"range":[172,1,174,11],"value":{"name":{"range":[172,1,172,5],"value":"view"},"arguments":[{"range":[172,6,172,11],"value":{"type":"var","var":{"value":"model"}}}],"expression":{"range":[173,5,174,11],"value":{"type":"application","application":[{"range":[173,5,173,8],"value":{"type":"functionOrValue","functionOrValue":{"moduleName":[],"name":"div"}}},{"range":[173,9,173,11],"value":{"type":"list","list":[]}},{"range":[174,9,174,11],"value":{"type":"list","list":[]}}]}}}}}}},{"range":[177,1,195,10],"value":{"type":"function","function":{"documentation":null,"signature":{"range":[177,1,177,18],"value":{"name":{"range":[177,1,177,7],"value":"myHero"},"typeAnnotation":{"range":[177,10,177,18],"value":{"type":"typed","typed":{"moduleNameAndName":{"range":[177,10,177,14],"value":{"moduleName":[],"name":"Html"}},"args":[{"range":[177,15,177,18],"value":{"type":"typed","typed":{"moduleNameAndName":{"range":[177,15,177,18],"value":{"moduleName":[],"name":"Msg"}},"args":[]}}}]}}}}},"declaration":{"range":[178,1,195,10],"value":{"name":{"range":[178,1,178,7],"value":"myHero"},"arguments":[],"expression":{"range":[179,5,195,10],"value":{"type":"application","application":[{"range":[179,5,179,13],"value":{"type":"functionOrValue","functionOrValue":{"moduleName":[],"name":"easyHero"}}},{"range":[180,9,184,10],"value":{"type":"parenthesized","parenthesized":{"range":[180,10,183,20],"value":{"type":"application","application":[{"range":[180,10,180,23],"value":{"type":"functionOrValue","functionOrValue":{"moduleName":[],"name":"HeroModifiers"}}},{"range":[181,13,181,18],"value":{"type":"functionOrValue","functionOrValue":{"moduleName":[],"name":"False"}}},{"range":[182,13,182,18],"value":{"type":"functionOrValue","functionOrValue":{"moduleName":[],"name":"Large"}}},{"range":[183,13,183,20],"value":{"type":"functionOrValue","functionOrValue":{"moduleName":[],"name":"Default"}}}]}}}},{"range":[185,9,185,11],"value":{"type":"list","list":[]}},{"range":[186,9,195,10],"value":{"type":"record","record":[{"range":[186,11,188,39],"value":{"field":{"range":[186,11,186,15],"value":"head"},"expression":{"range":[187,13,188,39],"value":{"type":"application","application":[{"range":[187,13,187,21],"value":{"type":"functionOrValue","functionOrValue":{"moduleName":[],"name":"heroHead"}}},{"range":[187,22,187,24],"value":{"type":"list","list":[]}},{"range":[188,17,188,39],"value":{"type":"list","list":[{"range":[188,19,188,37],"value":{"type":"application","application":[{"range":[188,19,188,27],"value":{"type":"functionOrValue","functionOrValue":{"moduleName":[],"name":"myNavbar"}}},{"range":[188,28,188,32],"value":{"type":"functionOrValue","functionOrValue":{"moduleName":[],"name":"True"}}},{"range":[188,33,188,37],"value":{"type":"functionOrValue","functionOrValue":{"moduleName":[],"name":"True"}}}]}}]}}]}}}},{"range":[189,11,192,9],"value":{"field":{"range":[189,11,189,15],"value":"body"},"expression":{"range":[190,13,191,19],"value":{"type":"application","application":[{"range":[190,13,190,21],"value":{"type":"functionOrValue","functionOrValue":{"moduleName":[],"name":"heroBody"}}},{"range":[190,22,190,24],"value":{"type":"list","list":[]}},{"range":[191,17,191,19],"value":{"type":"list","list":[]}}]}}}},{"range":[192,11,195,9],"value":{"field":{"range":[192,11,192,15],"value":"foot"},"expression":{"range":[193,13,194,19],"value":{"type":"application","application":[{"range":[193,13,193,21],"value":{"type":"functionOrValue","functionOrValue":{"moduleName":[],"name":"heroFoot"}}},{"range":[193,22,193,24],"value":{"type":"list","list":[]}},{"range":[194,17,194,19],"value":{"type":"list","list":[]}}]}}}}]}}]}}}}}}},{"range":[198,1,263,10],"value":{"type":"function","function":{"documentation":null,"signature":{"range":[198,1,198,36],"value":{"name":{"range":[198,1,198,9],"value":"myNavbar"},"typeAnnotation":{"range":[198,12,198,36],"value":{"type":"function","function":{"left":{"range":[198,12,198,16],"value":{"type":"typed","typed":{"moduleNameAndName":{"range":[198,12,198,16],"value":{"moduleName":[],"name":"Bool"}},"args":[]}}},"right":{"range":[198,20,198,36],"value":{"type":"function","function":{"left":{"range":[198,20,198,24],"value":{"type":"typed","typed":{"moduleNameAndName":{"range":[198,20,198,24],"value":{"moduleName":[],"name":"Bool"}},"args":[]}}},"right":{"range":[198,28,198,36],"value":{"type":"typed","typed":{"moduleNameAndName":{"range":[198,28,198,32],"value":{"moduleName":[],"name":"Html"}},"args":[{"range":[198,33,198,36],"value":{"type":"typed","typed":{"moduleNameAndName":{"range":[198,33,198,36],"value":{"moduleName":[],"name":"Msg"}},"args":[]}}}]}}}}}}}}}}},"declaration":{"range":[199,1,263,10],"value":{"name":{"range":[199,1,199,9],"value":"myNavbar"},"arguments":[{"range":[199,10,199,20],"value":{"type":"var","var":{"value":"isMenuOpen"}}},{"range":[199,21,199,39],"value":{"type":"var","var":{"value":"isMenuDropdownOpen"}}}],"expression":{"range":[200,5,263,10],"value":{"type":"application","application":[{"range":[200,5,200,11],"value":{"type":"functionOrValue","functionOrValue":{"moduleName":[],"name":"navbar"}}},{"range":[200,12,200,27],"value":{"type":"functionOrValue","functionOrValue":{"moduleName":[],"name":"navbarModifiers"}}},{"range":[201,9,201,11],"value":{"type":"list","list":[]}},{"range":[202,9,263,10],"value":{"type":"list","list":[{"range":[202,11,217,14],"value":{"type":"application","application":[{"range":[202,11,202,22],"value":{"type":"functionOrValue","functionOrValue":{"moduleName":[],"name":"navbarBrand"}}},{"range":[202,23,202,25],"value":{"type":"list","list":[]}},{"range":[203,13,210,14],"value":{"type":"parenthesized","parenthesized":{"range":[203,14,209,18],"value":{"type":"application","application":[{"range":[203,14,203,26],"value":{"type":"functionOrValue","functionOrValue":{"moduleName":[],"name":"navbarBurger"}}},{"range":[204,17,204,27],"value":{"type":"functionOrValue","functionOrValue":{"moduleName":[],"name":"isMenuOpen"}}},{"range":[205,17,205,19],"value":{"type":"list","list":[]}},{"range":[206,17,209,18],"value":{"type":"list","list":[{"range":[206,19,206,29],"value":{"type":"application","application":[{"range":[206,19,206,23],"value":{"type":"functionOrValue","functionOrValue":{"moduleName":[],"name":"span"}}},{"range":[206,24,206,26],"value":{"type":"list","list":[]}},{"range":[206,27,206,29],"value":{"type":"list","list":[]}}]}},{"range":[207,19,207,29],"value":{"type":"application","application":[{"range":[207,19,207,23],"value":{"type":"functionOrValue","functionOrValue":{"moduleName":[],"name":"span"}}},{"range":[207,24,207,26],"value":{"type":"list","list":[]}},{"range":[207,27,207,29],"value":{"type":"list","list":[]}}]}},{"range":[208,19,208,29],"value":{"type":"application","application":[{"range":[208,19,208,23],"value":{"type":"functionOrValue","functionOrValue":{"moduleName":[],"name":"span"}}},{"range":[208,24,208,26],"value":{"type":"list","list":[]}},{"range":[208,27,208,29],"value":{"type":"list","list":[]}}]}}]}}]}}}},{"range":[211,13,217,14],"value":{"type":"list","list":[{"range":[211,15,216,18],"value":{"type":"application","application":[{"range":[211,15,211,25],"value":{"type":"functionOrValue","functionOrValue":{"moduleName":[],"name":"navbarItem"}}},{"range":[211,26,211,31],"value":{"type":"functionOrValue","functionOrValue":{"moduleName":[],"name":"False"}}},{"range":[212,17,212,19],"value":{"type":"list","list":[]}},{"range":[213,17,216,18],"value":{"type":"list","list":[{"range":[213,19,215,40],"value":{"type":"application","application":[{"range":[213,19,213,28],"value":{"type":"functionOrValue","functionOrValue":{"moduleName":[],"name":"easyImage"}}},{"range":[213,29,213,36],"value":{"type":"functionOrValue","functionOrValue":{"moduleName":[],"name":"Natural"}}},{"range":[214,21,214,23],"value":{"type":"list","list":[]}},{"range":[215,21,215,40],"value":{"type":"literal","literal":"img\\elm_logo.png"}}]}}]}}]}}]}}]}},{"range":[218,11,262,14],"value":{"type":"application","application":[{"range":[218,11,218,21],"value":{"type":"functionOrValue","functionOrValue":{"moduleName":[],"name":"navbarMenu"}}},{"range":[218,22,218,32],"value":{"type":"functionOrValue","functionOrValue":{"moduleName":[],"name":"isMenuOpen"}}},{"range":[219,13,219,15],"value":{"type":"list","list":[]}},{"range":[220,13,262,14],"value":{"type":"list","list":[{"range":[220,15,225,18],"value":{"type":"application","application":[{"range":[220,15,220,26],"value":{"type":"functionOrValue","functionOrValue":{"moduleName":[],"name":"navbarStart"}}},{"range":[220,27,220,29],"value":{"type":"list","list":[]}},{"range":[221,17,225,18],"value":{"type":"list","list":[{"range":[221,19,221,58],"value":{"type":"application","application":[{"range":[221,19,221,33],"value":{"type":"functionOrValue","functionOrValue":{"moduleName":[],"name":"navbarItemLink"}}},{"range":[221,34,221,39],"value":{"type":"functionOrValue","functionOrValue":{"moduleName":[],"name":"False"}}},{"range":[221,40,221,42],"value":{"type":"list","list":[]}},{"range":[221,43,221,58],"value":{"type":"list","list":[{"range":[221,45,221,56],"value":{"type":"application","application":[{"range":[221,45,221,49],"value":{"type":"functionOrValue","functionOrValue":{"moduleName":[],"name":"text"}}},{"range":[221,50,221,56],"value":{"type":"literal","literal":"Home"}}]}}]}}]}},{"range":[222,19,222,58],"value":{"type":"application","application":[{"range":[222,19,222,33],"value":{"type":"functionOrValue","functionOrValue":{"moduleName":[],"name":"navbarItemLink"}}},{"range":[222,34,222,39],"value":{"type":"functionOrValue","functionOrValue":{"moduleName":[],"name":"False"}}},{"range":[222,40,222,42],"value":{"type":"list","list":[]}},{"range":[222,43,222,58],"value":{"type":"list","list":[{"range":[222,45,222,56],"value":{"type":"application","application":[{"range":[222,45,222,49],"value":{"type":"functionOrValue","functionOrValue":{"moduleName":[],"name":"text"}}},{"range":[222,50,222,56],"value":{"type":"literal","literal":"Blog"}}]}}]}}]}},{"range":[223,19,223,60],"value":{"type":"application","application":[{"range":[223,19,223,33],"value":{"type":"functionOrValue","functionOrValue":{"moduleName":[],"name":"navbarItemLink"}}},{"range":[223,34,223,38],"value":{"type":"functionOrValue","functionOrValue":{"moduleName":[],"name":"True"}}},{"range":[223,39,223,41],"value":{"type":"list","list":[]}},{"range":[223,42,223,60],"value":{"type":"list","list":[{"range":[223,44,223,58],"value":{"type":"application","application":[{"range":[223,44,223,48],"value":{"type":"functionOrValue","functionOrValue":{"moduleName":[],"name":"text"}}},{"range":[223,49,223,58],"value":{"type":"literal","literal":"Carrots"}}]}}]}}]}},{"range":[224,19,224,59],"value":{"type":"application","application":[{"range":[224,19,224,33],"value":{"type":"functionOrValue","functionOrValue":{"moduleName":[],"name":"navbarItemLink"}}},{"range":[224,34,224,39],"value":{"type":"functionOrValue","functionOrValue":{"moduleName":[],"name":"False"}}},{"range":[224,40,224,42],"value":{"type":"list","list":[]}},{"range":[224,43,224,59],"value":{"type":"list","list":[{"range":[224,45,224,57],"value":{"type":"application","application":[{"range":[224,45,224,49],"value":{"type":"functionOrValue","functionOrValue":{"moduleName":[],"name":"text"}}},{"range":[224,50,224,57],"value":{"type":"literal","literal":"About"}}]}}]}}]}}]}}]}},{"range":[226,15,261,18],"value":{"type":"application","application":[{"range":[226,15,226,24],"value":{"type":"functionOrValue","functionOrValue":{"moduleName":[],"name":"navbarEnd"}}},{"range":[226,25,226,27],"value":{"type":"list","list":[]}},{"range":[227,17,261,18],"value":{"type":"list","list":[{"range":[227,19,260,22],"value":{"type":"application","application":[{"range":[227,19,227,37],"value":{"type":"functionOrValue","functionOrValue":{"moduleName":[],"name":"navbarItemDropdown"}}},{"range":[227,38,227,56],"value":{"type":"functionOrValue","functionOrValue":{"moduleName":[],"name":"isMenuDropdownOpen"}}},{"range":[228,21,228,25],"value":{"type":"functionOrValue","functionOrValue":{"moduleName":[],"name":"Down"}}},{"range":[229,21,229,23],"value":{"type":"list","list":[]}},{"range":[230,21,234,22],"value":{"type":"parenthesized","parenthesized":{"range":[230,22,233,26],"value":{"type":"application","application":[{"range":[230,22,230,32],"value":{"type":"functionOrValue","functionOrValue":{"moduleName":[],"name":"navbarLink"}}},{"range":[231,25,231,27],"value":{"type":"list","list":[]}},{"range":[232,25,233,26],"value":{"type":"list","list":[{"range":[232,27,232,38],"value":{"type":"application","application":[{"range":[232,27,232,31],"value":{"type":"functionOrValue","functionOrValue":{"moduleName":[],"name":"text"}}},{"range":[232,32,232,38],"value":{"type":"literal","literal":"Menu"}}]}}]}}]}}}},{"range":[235,21,260,22],"value":{"type":"list","list":[{"range":[235,23,259,26],"value":{"type":"application","application":[{"range":[235,23,235,37],"value":{"type":"functionOrValue","functionOrValue":{"moduleName":[],"name":"navbarDropdown"}}},{"range":[235,38,235,43],"value":{"type":"functionOrValue","functionOrValue":{"moduleName":[],"name":"False"}}},{"range":[236,25,236,29],"value":{"type":"functionOrValue","functionOrValue":{"moduleName":[],"name":"Left"}}},{"range":[237,25,237,27],"value":{"type":"list","list":[]}},{"range":[238,25,259,26],"value":{"type":"list","list":[{"range":[238,27,244,30],"value":{"type":"application","application":[{"range":[238,27,238,41],"value":{"type":"functionOrValue","functionOrValue":{"moduleName":[],"name":"navbarItemLink"}}},{"range":[238,42,238,47],"value":{"type":"functionOrValue","functionOrValue":{"moduleName":[],"name":"False"}}},{"range":[239,29,239,31],"value":{"type":"list","list":[]}},{"range":[240,29,244,30],"value":{"type":"list","list":[{"range":[240,31,243,43],"value":{"type":"application","application":[{"range":[240,31,240,41],"value":{"type":"functionOrValue","functionOrValue":{"moduleName":[],"name":"easyButton"}}},{"range":[240,42,240,57],"value":{"type":"functionOrValue","functionOrValue":{"moduleName":[],"name":"buttonModifiers"}}},{"range":[241,33,241,35],"value":{"type":"list","list":[]}},{"range":[242,33,242,54],"value":{"type":"parenthesized","parenthesized":{"range":[242,34,242,53],"value":{"type":"application","application":[{"range":[242,34,242,44],"value":{"type":"functionOrValue","functionOrValue":{"moduleName":[],"name":"ChangePage"}}},{"range":[242,45,242,53],"value":{"type":"functionOrValue","functionOrValue":{"moduleName":[],"name":"Products"}}}]}}}},{"range":[243,33,243,43],"value":{"type":"literal","literal":"Products"}}]}}]}}]}},{"range":[245,27,251,30],"value":{"type":"application","application":[{"range":[245,27,245,41],"value":{"type":"functionOrValue","functionOrValue":{"moduleName":[],"name":"navbarItemLink"}}},{"range":[245,42,245,47],"value":{"type":"functionOrValue","functionOrValue":{"moduleName":[],"name":"False"}}},{"range":[246,29,246,31],"value":{"type":"list","list":[]}},{"range":[247,29,251,30],"value":{"type":"list","list":[{"range":[247,31,250,39],"value":{"type":"application","application":[{"range":[247,31,247,41],"value":{"type":"functionOrValue","functionOrValue":{"moduleName":[],"name":"easyButton"}}},{"range":[247,42,247,57],"value":{"type":"functionOrValue","functionOrValue":{"moduleName":[],"name":"buttonModifiers"}}},{"range":[248,33,248,35],"value":{"type":"list","list":[]}},{"range":[249,33,249,50],"value":{"type":"parenthesized","parenthesized":{"range":[249,34,249,49],"value":{"type":"application","application":[{"range":[249,34,249,44],"value":{"type":"functionOrValue","functionOrValue":{"moduleName":[],"name":"ChangePage"}}},{"range":[249,45,249,49],"value":{"type":"functionOrValue","functionOrValue":{"moduleName":[],"name":"Cart"}}}]}}}},{"range":[250,33,250,39],"value":{"type":"literal","literal":"Cart"}}]}}]}}]}},{"range":[252,27,258,30],"value":{"type":"application","application":[{"range":[252,27,252,41],"value":{"type":"functionOrValue","functionOrValue":{"moduleName":[],"name":"navbarItemLink"}}},{"range":[252,42,252,46],"value":{"type":"functionOrValue","functionOrValue":{"moduleName":[],"name":"True"}}},{"range":[253,29,253,31],"value":{"type":"list","list":[]}},{"range":[254,29,258,30],"value":{"type":"list","list":[{"range":[254,31,257,48],"value":{"type":"application","application":[{"range":[254,31,254,41],"value":{"type":"functionOrValue","functionOrValue":{"moduleName":[],"name":"easyButton"}}},{"range":[254,42,254,57],"value":{"type":"functionOrValue","functionOrValue":{"moduleName":[],"name":"buttonModifiers"}}},{"range":[255,33,255,35],"value":{"type":"list","list":[]}},{"range":[256,33,256,58],"value":{"type":"parenthesized","parenthesized":{"range":[256,34,256,57],"value":{"type":"application","application":[{"range":[256,34,256,44],"value":{"type":"functionOrValue","functionOrValue":{"moduleName":[],"name":"ChangePage"}}},{"range":[256,45,256,57],"value":{"type":"functionOrValue","functionOrValue":{"moduleName":[],"name":"OrderHistory"}}}]}}}},{"range":[257,33,257,48],"value":{"type":"literal","literal":"Order history"}}]}}]}}]}}]}}]}}]}}]}}]}}]}}]}}]}}]}}]}}}}}}}],"comments":[{"range":[119,1,119,8],"value":"-- VIEW"},{"range":[96,5,96,14],"value":"--dodelat"},{"range":[91,1,91,10],"value":"-- UPDATE"},{"range":[63,1,63,9],"value":"-- MODEL"},{"range":[44,1,44,3],"value":"--"},{"range":[26,1,26,8],"value":"-- MAIN"}]}